debyecalculator/.coverage
debyecalculator/__init__.py
debyecalculator/data/AntiFluorite_Co2O.cif
debyecalculator/data/AntiFluorite_Co2O_r10.xyz
debyecalculator/data/ICSD_CollCode1504.cif
debyecalculator/data/__init__.py
debyecalculator/data/icsd_000001_cc.cif
debyecalculator/data/icsd_000029_cc.cif
debyecalculator/data/icsd_001504_cc_r6_lc_2.85_6_tetragonal.xyz
debyecalculator/data/sim_Ag2O_cc_r4_lc_2.64_4_AntiFlourite.xyz
debyecalculator/debye_calculator.py
debyecalculator/display_assets/a.png
debyecalculator/display_assets/a_inv.png
debyecalculator/display_assets/a_sq.png
debyecalculator/display_assets/batch_size.png
debyecalculator/display_assets/choose_hardware.png
debyecalculator/display_assets/enter_path.png
debyecalculator/display_assets/file_1.png
debyecalculator/display_assets/file_2.png
debyecalculator/display_assets/fq.png
debyecalculator/display_assets/global_biso.png
debyecalculator/display_assets/gr.png
debyecalculator/display_assets/iq.png
debyecalculator/display_assets/iq_scaling.png
debyecalculator/display_assets/max_norm.png
debyecalculator/display_assets/presets.png
debyecalculator/display_assets/qdamp.png
debyecalculator/display_assets/qslider.png
debyecalculator/display_assets/qstep.png
debyecalculator/display_assets/radiation_type.png
debyecalculator/display_assets/radius_a.png
debyecalculator/display_assets/rslider.png
debyecalculator/display_assets/rstep.png
debyecalculator/display_assets/rthres.png
debyecalculator/display_assets/scattering_parameters.png
debyecalculator/display_assets/select_files.png
debyecalculator/display_assets/show_hide.png
debyecalculator/display_assets/sq.png
debyecalculator/htmlcov/__init___py.html
debyecalculator/htmlcov/coverage_html.js
debyecalculator/htmlcov/debye_calculator_py.html
debyecalculator/htmlcov/favicon_32.png
debyecalculator/htmlcov/index.html
debyecalculator/htmlcov/jquery.ba-throttle-debounce.min.js
debyecalculator/htmlcov/jquery.hotkeys.js
debyecalculator/htmlcov/jquery.isonscreen.js
debyecalculator-1.0.14.dist-info/LICENSE.txt
debyecalculator-1.0.14.dist-info/METADATA
debyecalculator-1.0.14.dist-info/WHEEL
debyecalculator-1.0.14.dist-info/RECORD
