Metadata-Version: 2.1
Name: debyecalculator
Version: 1.0.14
Summary: A vectorised implementation of the Debye Equation on CPU and GPU
Home-page: https://github.com/FrederikLizakJohansen/DebyeCalculator
License: Apache-2.0
Author: Frederik Lizak Johansen
Author-email: frjo@di.ku.dk
Requires-Python: >=3.7,<3.12
Classifier: License :: OSI Approved :: Apache Software License
Classifier: Operating System :: OS Independent
Classifier: Programming Language :: Python :: 3
Classifier: Programming Language :: Python :: 3.7
Classifier: Programming Language :: Python :: 3.8
Classifier: Programming Language :: Python :: 3.9
Classifier: Programming Language :: Python :: 3.10
Classifier: Programming Language :: Python :: 3.11
Classifier: Programming Language :: Python :: 3
Requires-Dist: ase (>=3.22.1,<3.23.0)
Requires-Dist: ipywidgets (>=8.0.3,<9.0.0)
Requires-Dist: matplotlib (>=3.4.3,<4.0.0) ; python_version >= "3.7" and python_version < "3.9"
Requires-Dist: matplotlib (>=3.8.0,<4.0.0) ; python_version >= "3.9" and python_version < "3.12"
Requires-Dist: notebook (>=6.4.1,<7.0.0)
Requires-Dist: numpy (>=1.21.5,<2.0.0) ; python_version == "3.7"
Requires-Dist: numpy (>=1.24.3,<2.0.0) ; python_version == "3.8"
Requires-Dist: numpy (>=1.26.0,<2.0.0) ; python_version >= "3.9" and python_version < "3.12"
Requires-Dist: prettytable (==3.0.0)
Requires-Dist: pymatgen (>=2020.0.0,<2024.9.10) ; python_version >= "3.10" and python_version < "4.0"
Requires-Dist: pyyaml (>=6.0.1,<7.0.0)
Requires-Dist: scipy (==1.7.3) ; python_version == "3.7"
Requires-Dist: scipy (>=1.7.3,<2.0.0) ; python_version >= "3.9" and python_version < "3.12"
Requires-Dist: tqdm (>=4.66.1,<5.0.0)
Project-URL: Repository, https://github.com/FrederikLizakJohansen/DebyeCalculator
